estare/__init__.py
estare/estare.py
estare_Egel-0.0.1.dist-info/LICENSE
estare_Egel-0.0.1.dist-info/METADATA
estare_Egel-0.0.1.dist-info/WHEEL
estare_Egel-0.0.1.dist-info/top_level.txt
estare_Egel-0.0.1.dist-info/RECORD
