Metadata-Version: 2.1
Name: estare-Egel
Version: 0.0.1
Summary: Package for stacking astrophoto images
Home-page: https://github.com/soheil-soltani/estare
Author: Soheil Soltani
Author-email: soheil@netc.eu
License: UNKNOWN
Platform: UNKNOWN
Classifier: Programming Language :: Python :: 3
Classifier: License :: OSI Approved :: GNU General Public License v3 (GPLv3)
Classifier: Operating System :: POSIX :: Linux
Requires-Python: >=3.6
